browserexport/__init__.pyi
browserexport/__main__.py
browserexport/common.py
browserexport/demo.py
browserexport/log.py
browserexport/merge.py
browserexport/model.py
browserexport/parse.py
browserexport/py.typed
browserexport/save.py
browserexport/sqlite.py
browserexport/browsers/__init__.pyi
browserexport/browsers/all.py
browserexport/browsers/arc.py
browserexport/browsers/brave.py
browserexport/browsers/chrome.py
browserexport/browsers/chromium.py
browserexport/browsers/common.py
browserexport/browsers/edge.py
browserexport/browsers/edgedev.py
browserexport/browsers/firefox.py
browserexport/browsers/firefox_mobile.py
browserexport/browsers/firefox_mobile_legacy.py
browserexport/browsers/floorp.py
browserexport/browsers/librewolf.py
browserexport/browsers/opera.py
browserexport/browsers/palemoon.py
browserexport/browsers/qutebrowser.py
browserexport/browsers/safari.py
browserexport/browsers/vivaldi.py
browserexport/browsers/waterfox.py
browserexport-0.4.4.dist-info/licenses/LICENSE
browserexport-0.4.4.dist-info/METADATA
browserexport-0.4.4.dist-info/WHEEL
browserexport-0.4.4.dist-info/entry_points.txt
browserexport-0.4.4.dist-info/top_level.txt
browserexport-0.4.4.dist-info/RECORD
