Metadata-Version: 2.4
Name: browserexport
Version: 0.4.4
Summary: save and merge browser history and metadata from different browsers
Author: purarue
License-Expression: MIT
Project-URL: Homepage, https://github.com/purarue/browserexport
Keywords: backup,brave,chrome,chromium,database,export,firefox,google-chrome,history,palemoon,safari,vivaldi,waterfox
Classifier: Programming Language :: Python
Classifier: Programming Language :: Python :: 3
Classifier: Programming Language :: Python :: 3 :: Only
Classifier: Programming Language :: Python :: 3.9
Classifier: Programming Language :: Python :: 3.10
Classifier: Programming Language :: Python :: 3.11
Classifier: Programming Language :: Python :: 3.12
Classifier: Programming Language :: Python :: 3.13
Requires-Python: >=3.9
License-File: LICENSE
Requires-Dist: click>=8.1
Requires-Dist: kompress>=0.1.20231016
Requires-Dist: logzero
Requires-Dist: sqlite-backup>=0.1.7
Provides-Extra: testing
Requires-Dist: flake8; extra == "testing"
Requires-Dist: mypy; extra == "testing"
Requires-Dist: pytest; extra == "testing"
Dynamic: license-file
